{
  "name": "Lora Ballard",
  "age": 44,
  "address": {
    "street": "Cufhes Plaza",
    "city": "Lahpolmu",
    "state": "KS",
    "zip": "72342"
  },
  "contact": {
    "phone": "(202) 756-7647",
    "servicePhone": "800861895"
  },
  "birthday": "2004-07-23T14:39:23.115Z",
  "ip": "124.94.252.69",
  "foo": "bar",
  "profile": {
    "about": "Wevat co lobbe rotkez ecorat tuwzo leebdac lurte uvjimiz ra oviud watabjo ara cuubu ohazak idgaf wigu. Galer rimiwan faojepaf epese kaffe wime dabium lezote bi re lotew fuce jug. Naawu oviode rodjelfi mucoc eravasara fafgo budugug ihju ga narrubroh joro ef riguves gilinkep imoomid kupnas.",
    "bio": "Mis lo ab wumogor kaghoca nik ve ile voc jukap gizu badwefvu akefug esvij bovu ninnit. Aruve liwov eslufbav nu bov ho zeguc jil rofte kuk ka tukunju. Sutac le livjewse idocawpu duzi rumamzi vebcutfu eketaova da lohuslo dede pansivbi tisvofdav gopuriw paw. Jotzabak vidpo vacag hotpad tab vozriod danefma de lavju ta zandiaci ur ba buwajok jiezzob dejzove."
  },
  "apiKey": "8cf284339a2e13b175a2f5d2b90b22c220443cc35870897dd1335b325c79fd90",
  "currency": {
    "code": "SLL",
    "name": "Sierra Leone Leone"
  }
}